gsstatic/__init__.py
gsstatic/_easywatch.py
gsstatic/library.py
gsstatic/reloader.py
gsstatic/static.py
gsstatic/utils.py
gsstatic-0.0.1.dist-info/METADATA
gsstatic-0.0.1.dist-info/WHEEL
gsstatic-0.0.1.dist-info/licenses/LICENSE
gsstatic-0.0.1.dist-info/RECORD
