Metadata-Version: 2.3
Name: gsstatic
Version: 0.0.1
Summary: A static site generator based on the Jinja2 templating engine.
Project-URL: Homepage, https://github.com/GSCS-AU/gsstatic
Project-URL: Issues, https://github.com/GSCS-AU/gsstatic/issues
Author-email: Paul Gower <pgower@gscs.au>
License-File: LICENSE
Keywords: jinja2,static site generator
Classifier: License :: OSI Approved :: MIT License
Classifier: Operating System :: OS Independent
Classifier: Programming Language :: Python :: 3
Requires-Python: >=3.8
Requires-Dist: jinja2
Requires-Dist: markupsafe
Requires-Dist: watchdog
